README.rst
setup.cfg
setup.py
exopy/__init__.py
exopy/__main__.py
exopy/version.py
exopy.egg-info/PKG-INFO
exopy.egg-info/SOURCES.txt
exopy.egg-info/dependency_links.txt
exopy.egg-info/entry_points.txt
exopy.egg-info/not-zip-safe
exopy.egg-info/requires.txt
exopy.egg-info/top_level.txt
exopy/app/__init__.py
exopy/app/api.py
exopy/app/app_extensions.py
exopy/app/app_manifest.enaml
exopy/app/app_plugin.py
exopy/app/dependencies/__init__.py
exopy/app/dependencies/api.py
exopy/app/dependencies/dependencies.py
exopy/app/dependencies/manifest.enaml
exopy/app/dependencies/plugin.py
exopy/app/errors/__init__.py
exopy/app/errors/api.py
exopy/app/errors/errors.py
exopy/app/errors/manifest.enaml
exopy/app/errors/plugin.py
exopy/app/errors/widgets.enaml
exopy/app/icons/__init__.py
exopy/app/icons/api.py
exopy/app/icons/icon_theme.py
exopy/app/icons/manifest.enaml
exopy/app/icons/plugin.py
exopy/app/log/__init__.py
exopy/app/log/manifest.enaml
exopy/app/log/plugin.py
exopy/app/log/tools.py
exopy/app/packages/__init__.py
exopy/app/packages/manifest.enaml
exopy/app/packages/plugin.py
exopy/app/preferences/__init__.py
exopy/app/preferences/api.py
exopy/app/preferences/manifest.enaml
exopy/app/preferences/plugin.py
exopy/app/preferences/preferences.py
exopy/app/states/__init__.py
exopy/app/states/api.py
exopy/app/states/manifest.enaml
exopy/app/states/plugin.py
exopy/app/states/state.py
exopy/instruments/__init__.py
exopy/instruments/api.py
exopy/instruments/infos.py
exopy/instruments/manifest.enaml
exopy/instruments/manufacturer_aliases.py
exopy/instruments/plugin.py
exopy/instruments/user.py
exopy/instruments/connections/__init__.py
exopy/instruments/connections/base_connection.py
exopy/instruments/connections/dll_connection.enaml
exopy/instruments/connections/visa_connections.enaml
exopy/instruments/drivers/__init__.py
exopy/instruments/drivers/driver_decl.py
exopy/instruments/settings/__init__.py
exopy/instruments/settings/base_settings.py
exopy/instruments/starters/__init__.py
exopy/instruments/starters/base_starter.py
exopy/instruments/starters/exceptions.py
exopy/instruments/widgets/__init__.py
exopy/instruments/widgets/browsing.enaml
