Metadata-Version: 1.1
Name: exopy
Version: 0.1.0
Summary: Experiment control application
Home-page: http://github.com/exopy/exopy
Author: Exopy Developers (see AUTHORS)
Author-email: m.dartiailh@gmail.com
License: BSD
Download-URL: http://github.com/exopy/exopy/tarball/master
Keywords: experiment automation GUI
Platform: UNKNOWN
Classifier: Development Status :: 3 - Alpha
Classifier: License :: OSI Approved :: BSD License
Classifier: Natural Language :: English
Classifier: Operating System :: OS Independent
Classifier: Topic :: Scientific/Engineering :: Physics
Classifier: Programming Language :: Python :: 2.7
Classifier: Programming Language :: Python :: 3.5
Classifier: Programming Language :: Python :: 3.6
Requires: future
Requires: pyqt
Requires: atom
Requires: enaml
Requires: kiwisolver
Requires: configobj
Requires: watchdog
Requires: setuptools
Requires: qtawesome
Requires: numpy
